{
    "version": "https://jsonfeed.org/version/1",
    "title": "新浪新闻",
    "home_page_url": "https://h52e5.github.io/sina-news/",
    "feed_url": "https://h52e5.github.io/sina-news/rss.json",
    "description": "新浪全球实时财经新闻",
    "items": [
        {
            "id": 3749738,
            "content_html": "",
            "url": "https://finance.sina.cn/7x24/2024-08-24/detail-incksqxt9068366.d.html",
            "title": "【“悟空”出圈又出海，文化贸易展现新动能】 以中国神话为背景的动作角色扮演游戏《黑神话：悟空》20日在全球正式发售。破石而出的《黑神话：悟空》搅动全球游戏圈，吸引了众多国内外玩家，不少外国玩家更因为这款游戏开始苦读《西游记》和恶补中文，甚至请假回家只为第一时间一睹悟空“真颜”……世界知名电子游戏数字发行平台Steam数据显示，截至目前，这款游戏在全球范围内稳居销量榜首，同时在线人数最高超过235万人。专家表示，《黑神话：悟空》是将中国文化装入到具象化的游戏产品中的成功尝试，是游戏出海的成功案例，有望为中国文化出口探索新的路径。（中证报）",
            "date_modified": "2024-08-23T21:05:32.000Z"
        },
        {
            "id": 3749737,
            "content_html": "",
            "url": "https://finance.sina.cn/7x24/2024-08-24/detail-incksqxt9068039.d.html",
            "title": "惠誉确认乌兹别克斯坦的评级为BB-。",
            "date_modified": "2024-08-23T21:04:29.000Z"
        },
        {
            "id": 3749736,
            "content_html": "",
            "url": "https://finance.sina.cn/7x24/2024-08-24/detail-incksqxs2290807.d.html",
            "title": "市场资讯：美国要求以色列从加沙与埃及边界地区撤军以与哈马斯达成协议。",
            "date_modified": "2024-08-23T21:04:11.000Z"
        },
        {
            "id": 3749733,
            "content_html": "",
            "title": "减肥药概念股普遍收涨，Ventyx Biosciences收涨14.72%，“平价减肥药”供应商Hims、硕迪生物ADR、安进至少涨超1.6%，诺和诺德ADR也涨不到0.1%，礼来则收跌超0.1%脱离收盘历史最高位。",
            "date_modified": "2024-08-23T20:53:54.000Z"
        },
        {
            "id": 3749732,
            "content_html": "",
            "url": "https://finance.sina.cn/7x24/2024-08-24/detail-incksqxt9065461.d.html",
            "title": "【5家银行理财子公司中期业绩出炉：理财规模扩大、3家公司营收净利双增长】 随着银行半年报的披露，上市银行旗下的理财子公司中期业绩随之浮出水面。截至8月23日，已有平安银行、浦发银行、兴业银行、江苏银行、南京银行等5家银行旗下的理财子公司中期业绩出炉。从产品规模来看，截至今年6月末，5家银行理财子公司理财产品规模均较去年同期有所增长，有的银行子公司理财产品规模同比增长近七成。从已披露数据来看，3家银行理财子公司实现营收和净利润同比双增长。（证券日报）",
            "date_modified": "2024-08-23T20:53:06.000Z"
        },
        {
            "id": 3749729,
            "content_html": "",
            "url": "https://finance.sina.cn/7x24/2024-08-24/detail-incksqxx7572877.d.html",
            "title": "【大模型与具身智能变现提速，国产机器人加速“出海”】 备受瞩目的2024世界机器人大会正如火如荼举行。大会发布的数据显示，中国已经在全球机器人创新、应用拓展和行业治理方面走在了国际前列。在本届大会上，六足机器人、低空机器人等各类新型机器人层出不穷。中国机器人厂商在大模型、多源信息融合感知、人机自然交互等前沿技术领域，以及传感器等关键环节不断取得突破。优必选、东港股份、首程控股、擎朗智能等多家上市公司及头部企业均在现场设展。多位企业负责人在现场表示，目前大模型正在逐步实现商业变现，公司加速推进AI大模型机器人“出海”。（证券日报）",
            "date_modified": "2024-08-23T20:37:51.000Z"
        },
        {
            "id": 3749728,
            "content_html": "",
            "url": "https://finance.sina.cn/7x24/2024-08-24/detail-incksqxs2283787.d.html",
            "title": "【北交所市场受拟上市企业青睐，严审核助力高质量扩容】 今年以来，北交所市场受到拟上市企业青睐。“上交所企业上市服务”发布最新发审信息显示，截至8月18日，今年新增申报企业32家，其中北交所30家。东源投资首席分析师刘祥东表示，随着北交所对创新型中小企业的吸引力日益增强，其高质量扩容的步伐也在加速推进。在这一过程中，北交所不仅展现了对创新型中小企业的包容性，审核程序的高效性，还坚持严格的上市审核标准，确保市场健康稳定发展。（证券日报）",
            "date_modified": "2024-08-23T20:35:05.000Z"
        },
        {
            "id": 3749726,
            "content_html": "",
            "url": "https://finance.sina.cn/7x24/2024-08-24/detail-incksqxs2282944.d.html",
            "title": "【联合国秘书长呼吁俄乌双方确保核电站安全】当地时间8月23日，联合国秘书长发言人迪雅里克在回答央视记者提问时表示，秘书长对扎波罗热和库尔斯克两座核电站近期出现的一系列事件感到担忧，呼吁俄乌双方确保核电站的安全。迪雅里克表示，“我想所有人都应该担心，这两座核电站都在冲突地区，确实是有危险的。所以我们从一开始就呼吁，所有相关各方—乌克兰和俄罗斯要确保核电站的安全和得到保护。”迪雅里克还呼吁各方应该就核电站安全与国际原子能机构进行协作。",
            "date_modified": "2024-08-23T20:32:51.000Z"
        },
        {
            "id": 3749725,
            "content_html": "",
            "url": "https://finance.sina.cn/7x24/2024-08-24/detail-incksqxs2282525.d.html",
            "title": "【美国宣布向乌克兰提供新一批军事援助】当地时间8月23日，美国总统拜登在白宫发表声明，称他当天与乌克兰总统泽连斯基进行了电话会谈，并宣布美国将为乌克兰提供新的军事援助。拜登在声明中称，为乌克兰提供的新的一揽子军事援助包括防空导弹、反无人机设备、反装甲导弹、弹药等。",
            "date_modified": "2024-08-23T20:30:56.000Z"
        },
        {
            "id": 3749720,
            "content_html": "",
            "url": "https://finance.sina.cn/7x24/2024-08-24/detail-incksqxs2281148.d.html",
            "title": "标普确认奥地利AA+评级，前景展望从稳定上调至正面。",
            "date_modified": "2024-08-23T20:22:51.000Z"
        },
        {
            "id": 3749717,
            "content_html": "",
            "url": "https://finance.sina.cn/7x24/2024-08-24/detail-incksqxs2279356.d.html",
            "title": "【以军称监测到约10枚火箭弹从黎南部进入以色列境内】当地时间23日夜间，以色列北部基尔亚特什莫纳等地响起防空警报。以色列国防军随后发表声明称，监测到约10枚火箭弹从黎巴嫩南部进入以色列境内，以军防空系统拦截了部分火箭弹，事件没有造成人员伤亡。",
            "date_modified": "2024-08-23T20:11:39.000Z"
        },
        {
            "id": 3749716,
            "content_html": "",
            "title": "美国商品期货交易委员会（CFTC）：8月20日当周，对冲基金情绪反转，重新看空日元。",
            "date_modified": "2024-08-23T20:07:35.000Z"
        },
        {
            "id": 3749713,
            "content_html": "",
            "title": "市场消息：Meta Platforms(META.O)封锁了与伊朗团体相关的WhatsApp账户。",
            "date_modified": "2024-08-23T20:03:17.000Z"
        },
        {
            "id": 3749712,
            "content_html": "",
            "url": "https://finance.sina.cn/7x24/2024-08-24/detail-incksqxt9055033.d.html",
            "title": "【“巨无霸”频现，8只宽基ETF规模合计破万亿元】 ETF市场亮点频现。最新募集成立的融通中证诚通央企科技创新ETF发行规模达17.85亿元，创今年以来主题型ETF募集规模新高。同时，A股宽基ETF“巨无霸”也变得更大了——华泰柏瑞沪深300ETF规模突破2700亿元，易方达沪深300ETF规模超过1800亿元。8只A股宽基ETF规模合计突破万亿元。宽基ETF强者恒强，吸引了不少基金公司入局。为大力发展指数业务，多家基金公司大力招揽人才。可以预见，ETF战火将越烧越旺。（上证报）",
            "date_modified": "2024-08-23T20:01:30.000Z"
        },
        {
            "id": 3749709,
            "content_html": "",
            "title": "以色列国防军：不久前黎巴嫩向谢莫纳城发射了10枚火箭弹，一些被拦截，没有人员伤亡报告。",
            "date_modified": "2024-08-23T19:59:57.000Z"
        },
        {
            "id": 3749707,
            "content_html": "",
            "url": "https://finance.sina.cn/7x24/2024-08-24/detail-incksqxw0802848.d.html",
            "title": "【美银：鸽派的鲍威尔发言仍未给降息50bp背书】美国银行经济学家在一份关于鲍威尔周五在杰克逊霍尔会议发表讲话的报告中表示，美联储对美国劳动力市场降温的关注仍要求9月份降息25个基点，而不是50个基点。美银表示，尽管鲍威尔的语气较为鸽派，但“我们不认为他为降息50个基点打开了更多的大门。”“相反，他含蓄地支持逐步削减利率。”如果经济衰退的风险上升，更大幅度的削减将会发生。“一份非常疲弱的就业报告可能会让我们实现这一目标，但申请失业救济人数的下降表明，这不应该是基本情况。”",
            "date_modified": "2024-08-23T19:58:02.000Z"
        },
        {
            "id": 3749706,
            "content_html": "",
            "title": "美国商品期货交易委员会（CFTC）：8月20日当周，对冲基金迅速加仓美国10年期国债期货。",
            "date_modified": "2024-08-23T19:55:51.000Z"
        },
        {
            "id": 3749704,
            "content_html": "",
            "url": "https://finance.sina.cn/7x24/2024-08-24/detail-incksqxt9053365.d.html",
            "title": "【亚洲宠物展规模再创新高，行业呈现消费升级趋势】 8月21日~25日，2024年亚洲宠物展在上海举行。作为亚洲最具影响力的宠物行业展会之一，亚宠展开幕首日火爆，宠物食品、宠物用品、医疗营养板块占据展馆主要人气。在国内宠物数量增长和结构性升级的驱动下，宠物行业在近年来持续保持较高增速。近期A股宠物行业上市公司发布的半年报或半年报预告纷纷报喜。多家宠物食品、宠物用品企业负责人表示，国内宠物市场当前进入相对稳定的增长阶段，无论是宠物食品还是宠物用品，行业整体存在产品同质化问题，未来破局之道在于打造差异化大单品与品牌运营。（证券时报）",
            "date_modified": "2024-08-23T19:51:41.000Z"
        },
        {
            "id": 3749703,
            "content_html": "",
            "title": "据美国商品期货交易委员会（CFTC）的最新数据，最近一周，杠杆基金对美国两年期国债期货的净空头头寸达到了历史最高水平。杠杆基金在美国10年期国债期货上的净空头头寸创下历史新高。",
            "date_modified": "2024-08-23T19:51:20.000Z"
        },
        {
            "id": 3749702,
            "content_html": "",
            "url": "https://finance.sina.cn/7x24/2024-08-24/detail-incksqxx7567025.d.html",
            "title": "市场资讯：阿根廷罗萨里奥机场报告可能发生炸弹事件。",
            "date_modified": "2024-08-23T19:50:21.000Z"
        },
        {
            "id": 3749701,
            "content_html": "",
            "url": "https://finance.sina.cn/7x24/2024-08-24/detail-incksqxs2275580.d.html",
            "title": "市场资讯：阿根廷总统米莱将要发表讲话的地方收到炸弹威胁。",
            "date_modified": "2024-08-23T19:48:54.000Z"
        },
        {
            "id": 3749700,
            "content_html": "",
            "url": "https://finance.sina.cn/7x24/2024-08-24/detail-incksqxt9052143.d.html",
            "title": "【机构：就业报告似乎比通胀更为重要】在杰克逊霍尔会议的讲话中，美联储主席鲍威尔强调了美国就业数据对即将到来的货币宽松周期的重要性。桑坦德银行的Stephen Stanley在一份报告中表示，这增加了将于9月6日公布的8月份就业数据的重要性。他表示，在7月份就业增长出人意料地低迷之后，“8月份的增长并不会完全令人震惊。更广泛地说，鲍威尔和美联储的其他人最近已经开始对劳动力市场状况的降温表示担忧，因此，8月份更为强劲的数据可能会打消下个月降息50个基点的想法。”Stanley认为，就业报告可能比8月核心CPI数据更为关键。",
            "date_modified": "2024-08-23T19:47:42.000Z"
        },
        {
            "id": 3749699,
            "content_html": "",
            "url": "https://finance.sina.cn/7x24/2024-08-24/detail-incksqxs2273843.d.html",
            "title": "【上半年生猪市场行情回暖，A股猪企业绩普遍好转、扩张仍谨慎】 进入2024年，尤其是第二季度之后，全国猪价逐月攀升，从年初14元/kg以下，涨至目前的20元/kg以上，创2022年12月上旬以来新高。根据已披露数据显示，A股五成生猪养殖企业2024年上半年实现盈利，九成上市猪企第二季度业绩将盈利或减亏。当前，能繁母猪存栏数持续降低、非洲猪瘟暴发等多重因素叠加，形成生猪供给缺口，猪价实现上涨。但本轮猪价上行期间，生猪养殖市场较为理性和谨慎，猪企进场积极性未见大幅提升，不再敢做大规模的扩张。下半年，业界希望能够保住目前的猪价高位，没有让猪价疯涨的动力。（证券时报）",
            "date_modified": "2024-08-23T19:43:38.000Z"
        },
        {
            "id": 3749697,
            "content_html": "",
            "url": "https://finance.sina.cn/7x24/2024-08-24/detail-incksqxs2273182.d.html",
            "title": "乌克兰总统泽连斯基：乌克兰迫切需要新的美国军事援助，特别是空中防御系统。",
            "date_modified": "2024-08-23T19:40:19.000Z"
        },
        {
            "id": 3749694,
            "content_html": "",
            "title": "美国白宫：总统拜登与卡塔尔埃米尔进行了交谈，并单独与埃及总统塞西进行了会谈，讨论加沙问题。",
            "date_modified": "2024-08-23T19:38:23.000Z"
        },
        {
            "id": 3749693,
            "content_html": "",
            "url": "https://finance.sina.cn/7x24/2024-08-24/detail-incksqxs2272623.d.html",
            "title": "埃及总统府：总统塞西与美国总统拜登在电话中回顾了最新一轮加沙停火谈判的进展。总统塞西与美国总统拜登表示，冲突各方展现灵活性以达成协议至关重要。",
            "date_modified": "2024-08-23T19:37:58.000Z"
        },
        {
            "id": 3749692,
            "content_html": "",
            "url": "https://finance.sina.cn/7x24/2024-08-24/detail-incksqxw0799670.d.html",
            "title": "【美国CFTC：黄金看涨情绪创四年新高】 美国商品期货交易委员会（CFTC）：8月20日当周，投机者所持COMEX黄金净多头头寸增加17,077手合约，至236,749手合约，创逾四年新高。8月20日21:30，现货黄金涨至2531.75美元/盎司，COMEX黄金期货当时也涨至2570.40美元，双双创历史新高。所持COMEX白银净多头头寸增至31,998手合约，创五周新高。所持COMEX铜净多头头寸增至14,041手合约，创四周新高。转而持有NYMEX铂金净多头头寸82手合约，为三周以来新高；之前一周持有净空头头寸2,224手合约。所持NYMEX钯金净空头头寸降至14,856手合约，创四周新低。",
            "date_modified": "2024-08-23T19:37:12.000Z"
        },
        {
            "id": 3749689,
            "content_html": "",
            "url": "https://finance.sina.cn/7x24/2024-08-24/detail-incksqxt9048019.d.html",
            "title": "【俄罗斯罗斯托夫州一地发生火灾 暂无人员伤亡】俄罗斯紧急情况部当地时间23日发布消息称，罗斯托夫州普罗列塔尔斯克发生火灾，地面上的干燥植被起火燃烧并已经扩散到了邻近的居民住宅。目前有40余人和12台设备正在参与灭火，暂时没有人员伤亡的消息。当地媒体报道称，起火的普罗列塔尔斯克油库目前已经燃烧了六天，23日出现的新火情和油库火灾没有直接联系，两处起火现场距离约为5公里。",
            "date_modified": "2024-08-23T19:27:36.000Z"
        },
        {
            "id": 3749687,
            "content_html": "",
            "url": "https://finance.sina.cn/7x24/2024-08-24/detail-inckskru2399056.d.html",
            "title": "【以军袭击加沙多地 巴勒斯坦武装组织打击以军目标】过去一天，以军继续在加沙地带多地开展军事行动，巴勒斯坦武装组织23日对以军人员和装备进行打击。与此同时，以色列与黎巴嫩真主党的冲突持续。以色列国防军23日称，以军过去一天在加沙地带中部和南部的战斗中消灭了数十名巴勒斯坦武装人员。此外，以色列空军在过去一天袭击了加沙地带约30个目标，包括汗尤尼斯地区的军事建筑、哨所、武器库等。23日，哈马斯下属武装派别“卡桑旅”称，在加沙城南部与以军士兵发生激烈冲突，造成部分以军士兵伤亡。在加沙地带南部城市拉法，卡桑旅武装人员用火箭弹袭击了以军士兵和坦克。此外，巴勒斯坦伊斯兰武装派别“圣城旅”23日发表声明称，其武装人员当天在加沙城用迫击炮袭击了以军。",
            "date_modified": "2024-08-23T19:13:24.000Z"
        },
        {
            "id": 3749685,
            "content_html": "",
            "title": "美国国防部宣布，国务院已决定批准向澳大利亚出售价值3亿美元的AH-64E阿帕奇直升机维持支持服务及相关设备。",
            "date_modified": "2024-08-23T19:07:12.000Z"
        },
        {
            "id": 3749682,
            "content_html": "",
            "url": "https://finance.sina.cn/7x24/2024-08-24/detail-inckskry0925951.d.html",
            "title": "【小肯尼迪表示他现在将支持唐纳德·特朗普】美国总统独立候选人小罗伯特·肯尼迪：我不再相信我有现实的途径获得选举胜利。我决定暂停我的竞选活动。将在10个关键州的选票上移除我的名字。我将暂停而非终止竞选活动。我的名字将在某些地区的选票上保留。小罗伯特·肯尼迪表示他现在将支持唐纳德·特朗普，称在许多关键问题上与美国前总统特朗普意见一致。",
            "date_modified": "2024-08-23T19:02:33.000Z"
        },
        {
            "id": 3749680,
            "content_html": "",
            "url": "https://finance.sina.cn/7x24/2024-08-24/detail-inckskrv9173798.d.html",
            "title": "【俄罗斯罗斯托夫州暂停一切大型户外活动】俄罗斯罗斯托夫州州长23日晚发表声明称，该州即日起暂时禁止举办一切大型户外活动。计划在室内场所举行的活动不受此禁令影响，但必须采取必要的安全措施。禁令持续时间另行规定。",
            "date_modified": "2024-08-23T19:00:27.000Z"
        },
        {
            "id": 3749679,
            "content_html": "",
            "url": "https://finance.sina.cn/7x24/2024-08-24/detail-inckskru2396621.d.html",
            "title": "【小罗伯特·肯尼迪在法庭文件中表示计划支持特朗普 其助手随后给予否认】综合多家媒体报道，小罗伯特·肯尼迪的竞选团队对宾夕法尼亚州的一家法院表示，他将支持前总统特朗普。当地时间周五下午，他宣布将结束独立总统竞选。在宾夕法尼亚州的一起与他自己在该州选票获取挑战相关的诉讼中，文件称“由于今天支持特朗普竞选美国总统”，他将退出投票。在肯尼迪的竞选伙伴本周开始公开考虑他是否会退出竞选以支持前总统特朗普之后，其结束竞选的决定就在意料之中了。不过肯尼迪的助手在这一报道后表示，肯尼迪尚未支持特朗普，法院文件并没有经过竞选团队审查。",
            "date_modified": "2024-08-23T19:00:08.000Z"
        },
        {
            "id": 3749676,
            "content_html": "",
            "url": "https://finance.sina.cn/7x24/2024-08-24/detail-inckskru2393933.d.html",
            "title": "市场消息：美国总统拜登宣布了一项针对乌克兰的新军事援助计划。美国总统拜登表示，对乌克兰的新军事援助计划包括防空导弹、反无人机设备、反装甲导弹和弹药。",
            "date_modified": "2024-08-23T18:44:56.000Z"
        },
        {
            "id": 3749673,
            "content_html": "",
            "url": "https://finance.sina.cn/7x24/2024-08-24/detail-inckskrv9169855.d.html",
            "title": "【乌兹别克斯坦与阿塞拜疆总统讨论深化两国关系等问题】乌兹别克斯坦总统米尔济约耶夫23日与阿塞拜疆总统阿利耶夫在塔什干举行会晤，双方就继续深化和扩大两国战略伙伴关系和多领域合作进行了磋商。根据乌兹别克斯坦总统网站当天发表的声明，米尔济约耶夫说，此次访问的重要成果之一就是双方签订盟友关系条约，这一条约开启了巩固两国协作的新篇章，表明双方全面发展多领域伙伴关系的意愿。声明说，两国还举行了高级别国家间委员会第一次会议，这一会议将成为制定和落实两国加深盟友关系相关举措的有效机制。（新华社）",
            "date_modified": "2024-08-23T18:37:50.000Z"
        },
        {
            "id": 3749672,
            "content_html": "",
            "url": "https://finance.sina.cn/7x24/2024-08-24/detail-inckskrv9169468.d.html",
            "title": "美国白宫：美国总统拜登于周五与乌克兰总统泽连斯基进行了电话沟通。",
            "date_modified": "2024-08-23T18:36:05.000Z"
        },
        {
            "id": 3749668,
            "content_html": "",
            "title": "土耳其财长Simsek：经济计划得到总统埃尔多安的全面支持，经济计划正成功地运作着。",
            "date_modified": "2024-08-23T18:30:31.000Z"
        },
        {
            "id": 3749667,
            "content_html": "",
            "url": "https://finance.sina.cn/7x24/2024-08-24/detail-inckskrv9167148.d.html",
            "title": "市场资讯：淡水河谷将于9月宣布新任首席执行官。",
            "date_modified": "2024-08-23T18:23:47.000Z"
        },
        {
            "id": 3749666,
            "content_html": "",
            "url": "https://finance.sina.cn/7x24/2024-08-24/detail-inckskrz7684830.d.html",
            "title": "叙利亚国家通讯社：以色列对叙利亚中部地区的空袭造成七名平民受伤。",
            "date_modified": "2024-08-23T18:21:51.000Z"
        },
        {
            "id": 3749665,
            "content_html": "",
            "url": "https://finance.sina.cn/7x24/2024-08-24/detail-inckskrv9166709.d.html",
            "title": "市场消息：苹果(AAPL.O)还加大了对配备M4处理器的MAC机型的测试力度。",
            "date_modified": "2024-08-23T18:21:05.000Z"
        },
        {
            "id": 3749662,
            "content_html": "",
            "title": "美国汽车工人联合会：Julian Electric的工人申请举行工会选举，以加入UAW。",
            "date_modified": "2024-08-23T18:16:37.000Z"
        },
        {
            "id": 3749660,
            "content_html": "",
            "url": "https://finance.sina.cn/7x24/2024-08-24/detail-inckskrv9165726.d.html",
            "title": "【分析师：美元正接近美联储开始加息以来的最低水平】在美联储主席鲍威尔几乎暗示结束了美联储的通胀斗争之后，美元星期五跌至近乎加息以来的最低水平。数据显示，美元兑一篮子货币的汇率创下52周新低，延续了近期因预期未来几个月将降息而导致的跌势。政策的改变有望改变资本在全球市场的流动方向。不过美元的走软往往有助于美国公司向海外销售商品和服务。",
            "date_modified": "2024-08-23T18:14:25.000Z"
        },
        {
            "id": 3749659,
            "content_html": "",
            "url": "https://finance.sina.cn/7x24/2024-08-24/detail-inckskry0918765.d.html",
            "title": "市场资讯：小罗伯特·肯尼迪在法庭文件中表示计划支持特朗普。",
            "date_modified": "2024-08-23T18:13:48.000Z"
        },
        {
            "id": 3749655,
            "content_html": "",
            "title": "以色列国防军：今天大约有100枚火箭弹从黎巴嫩向以色列北部发射，最新的40枚火箭弹袭击了谢莫纳城。",
            "date_modified": "2024-08-23T18:10:10.000Z"
        },
        {
            "id": 3749652,
            "content_html": "",
            "title": "Kraken必须就加密数字货币交易登记注册问题面临美国证券交易委员会（SEC）的诉讼。",
            "date_modified": "2024-08-23T18:00:26.000Z"
        },
        {
            "id": 3749650,
            "content_html": "",
            "url": "https://finance.sina.cn/7x24/2024-08-24/detail-inckskry0916337.d.html",
            "title": "市场消息：加纳将要求贸易商就可可豆预付款项。",
            "date_modified": "2024-08-23T17:56:17.000Z"
        },
        {
            "id": 3749649,
            "content_html": "",
            "url": "https://finance.sina.cn/7x24/2024-08-24/detail-inckskrv9161854.d.html",
            "title": "乌克兰国防部长：拉脱维亚将向乌克兰军方提供数千架无人机。拉脱维亚对乌克兰的军事支持在2024年将达到约1.12亿欧元。",
            "date_modified": "2024-08-23T17:51:03.000Z"
        },
        {
            "id": 3749648,
            "content_html": "",
            "url": "https://finance.sina.cn/7x24/2024-08-24/detail-inckskrz7680625.d.html",
            "title": "美联储古尔斯比：拖欠贷款和失业率发出“警告”。",
            "date_modified": "2024-08-23T17:50:51.000Z"
        },
        {
            "id": 3749646,
            "content_html": "",
            "url": "https://finance.sina.cn/7x24/2024-08-24/detail-inckskrz7680128.d.html",
            "title": "美国能源部：没有迹象表明哈利伯顿遭遇网络袭击影响到能源业。",
            "date_modified": "2024-08-23T17:48:04.000Z"
        },
        {
            "id": 3749645,
            "content_html": "",
            "url": "https://finance.sina.cn/7x24/2024-08-24/detail-inckskry0914905.d.html",
            "title": "美联储古尔斯比：鲍威尔的利率评论明确而坚定。资金利率设定在通货膨胀率高得多的时候。随着通胀降温，美联储政策已被动收紧。有充分理由认为美联储关于降息的预测将会实现。已收到就业市场的警示信号。",
            "date_modified": "2024-08-23T17:47:32.000Z"
        },
        {
            "id": 3749644,
            "content_html": "",
            "url": "https://finance.sina.cn/7x24/2024-08-24/detail-inckskrv9160554.d.html",
            "title": "【油服巨头哈里伯顿在遭受网络攻击后关闭了部分系统】全球油服巨头哈里伯顿表示，在本周早些时候遭受网络攻击后，他们已经关闭了部分内部系统。在周四提交给政府监管机构的一份简短声明中，哈里伯顿表示，它在周三意识到其系统遭到未经授权的访问，并采取了“主动关闭某些系统”的应对措施。该公司表示，正在“努力确定该事件的任何影响”。",
            "date_modified": "2024-08-23T17:44:29.000Z"
        },
        {
            "id": 3749643,
            "content_html": "",
            "title": "法国人工智能（AI）初创公司H：由于“运营思路差异”的缘故，三名联合创始人（最初由五人创建）离职。",
            "date_modified": "2024-08-23T17:39:24.000Z"
        },
        {
            "id": 3749642,
            "content_html": "",
            "url": "https://finance.sina.cn/7x24/2024-08-24/detail-inckskru2382358.d.html",
            "title": "美国油服公司哈利伯顿向石油客户们发出警告，该公司此前遭遇网络袭击。",
            "date_modified": "2024-08-23T17:38:35.000Z"
        },
        {
            "id": 3749640,
            "content_html": "",
            "url": "https://finance.sina.cn/7x24/2024-08-24/detail-inckskru2381948.d.html",
            "title": "【国际原子能机构：扎波罗热核电站一度陷入对单一电源依赖】当地时间23日，国际原子能机构表示，扎波罗热核电站22日与其唯一剩余的场外备用电源线失去连接，导致其再次陷入对单一电源的依赖。",
            "date_modified": "2024-08-23T17:36:20.000Z"
        },
        {
            "id": 3749638,
            "content_html": "",
            "title": "乌克兰总统泽连斯基在与印度总理会晤后表示：印度支持我们的主权和领土完整，这对我们至关重要。",
            "date_modified": "2024-08-23T17:30:31.000Z"
        }
    ]
}