{
    "version": "https://jsonfeed.org/version/1",
    "title": "新浪新闻",
    "home_page_url": "https://h52e5.github.io/sina-news/",
    "feed_url": "https://h52e5.github.io/sina-news/rss.json",
    "description": "新浪全球实时财经新闻",
    "items": [
        {
            "id": 2895725,
            "content_html": "",
            "url": "https://finance.sina.cn/7x24/2022-12-07/detail-imqmmthc7325469.d.html",
            "title": "  【美将向波兰出售37.5亿美元武器】当地时间12月6日，美国国防部表示，美国务院已批准向波兰出售116辆M1A1“艾布拉姆斯”坦克以及其他车辆和弹药等军备，总价值高达37.5亿美元。批准出售的军备中还包括修复受损坦克的车辆、8座突击桥和其他军用车辆。美国防部表示，还将向波兰提供穿甲弹、备件和技术支持等。（央视）",
            "date_modified": "2022-12-07T06:05:21.000Z"
        },
        {
            "id": 2895724,
            "content_html": "",
            "url": "https://finance.sina.cn/7x24/2022-12-07/detail-imqqsmrp8863908.d.html",
            "title": "【携程：2023年旅行搜索量同比上涨超900%】从携程处获悉，截至今日12时，本周内2023年出行搜索热度较去年同期（2021年搜索2022年）上涨超过900%。在今日上午发布元旦假期安排后的两小时内，携程机票、酒店产品搜索量环比前一日同时段增长分别达到6倍与7倍。",
            "date_modified": "2022-12-07T06:05:04.000Z"
        },
        {
            "id": 2895721,
            "content_html": "",
            "title": "  【德防长：德联邦议会将就是否斥资100亿欧元购买F-35战机做决定】据路透社报道，德国国防部长克里斯蒂娜·兰布雷希特当地时间6日表示，德国联邦议会将于12月中旬就是否以100亿欧元（约合人民币730亿元）的价格总额购买美国军工巨头洛克希德·马丁公司生产的F-35战斗机做出决定。 “我们将在 12 月 14 日的（议会）预算委员会的下一次会议上讨论一个巨大项目，即有关F-35……总金额达 100 亿欧元。”兰布雷希特在德国西部的行程中告诉记者。 （环球网）",
            "date_modified": "2022-12-07T06:03:42.000Z"
        },
        {
            "id": 2895717,
            "content_html": "",
            "url": "https://finance.sina.cn/7x24/2022-12-07/detail-imqmmthc7324307.d.html",
            "title": "  【韩政府：货运工会罢工已造成上百亿损失】韩国政府7日警告，持续2周的货运司机罢工已给钢铁、炼油、石化等行业造成3.5万亿韩元（约合人民币184亿元）的损失，敦促拒运司机尽早返岗。",
            "date_modified": "2022-12-07T05:52:52.000Z"
        },
        {
            "id": 2895716,
            "content_html": "",
            "url": "https://finance.sina.cn/7x24/2022-12-07/detail-imqqsmrp8862746.d.html",
            "title": "  【Meta的定向广告模式或在欧洲面临监管限制】欧盟隐私监管机构裁定，Meta Platforms Inc不应要求用户同意根据他们的在线活动投放个性化广告，这一裁决可能会限制Meta为出售此类广告所能获取的数据。一个代表所有欧盟隐私监管机构的委员会周一批准了一系列决定，裁定欧盟隐私法不允许Meta平台(如Instagram和Facebook)以其服务条款作为允许此类广告的理由。欧盟新做出的裁决可以被上诉，这可能导致这些裁决被暂停实施，面临潜在漫长的诉讼。",
            "date_modified": "2022-12-07T05:52:41.000Z"
        },
        {
            "id": 2895713,
            "content_html": "",
            "url": "https://finance.sina.cn/7x24/2022-12-07/detail-imqqsmrp8862208.d.html",
            "title": "【寿仙谷：公司第三代去壁灵芝孢子粉系列产品具有提高免疫力功效】寿仙谷在互动平台表示，公司第三代去壁灵芝孢子粉系列产品具有从本源上提高免疫力的功效，没有毒副作用，流感病毒患者以及想预防流感的健康人群均可以长期服用。",
            "date_modified": "2022-12-07T05:46:32.000Z"
        },
        {
            "id": 2895712,
            "content_html": "",
            "url": "https://finance.sina.cn/7x24/2022-12-07/detail-imqqsmrp8862153.d.html",
            "title": "  【不得限制购买退热止咳等非处方药】保障群众基本购药需求：各地药店要正常运营，不得随意关停。不得限制群众线上线下购买退热、止咳、抗病毒、治感冒等非处方药物。   （人民日报）",
            "date_modified": "2022-12-07T05:46:04.000Z"
        },
        {
            "id": 2895708,
            "content_html": "",
            "url": "https://finance.sina.cn/7x24/2022-12-07/detail-imqqsmrp8861555.d.html",
            "title": "  【辉瑞与Clear Creek Bio合作开发口服COVID-19药物】辉瑞公司和Clear Creek Bio Inc周二宣布合作，将共同开发一种新型口服治疗药物来对抗COVID-19。辉瑞公司首席科学官夏洛特·阿勒顿 (Charlotte Allerton) 表示，COVID-19有可能在未来几年继续成为全球健康问题。",
            "date_modified": "2022-12-07T05:40:34.000Z"
        },
        {
            "id": 2895705,
            "content_html": "",
            "url": "https://finance.sina.cn/7x24/2022-12-07/detail-imqqsmrp8861363.d.html",
            "title": "  【美国10月贸易逆差扩大 因能源出口减少】美国商务部周二表示，经季节性因素调整后，10月份商品和服务贸易逆差扩大到782亿美元，高于9月份修正后的741亿美元。出口下降0.7%，至2,566亿美元，反映出天然气、石油和药品的出口量减少。进口继续增长，上升0.6%至3,348亿美元，部分原因是美国对能源产品、车辆和药品的购买量增加。",
            "date_modified": "2022-12-07T05:39:19.000Z"
        },
        {
            "id": 2895683,
            "content_html": "",
            "url": "https://finance.sina.cn/7x24/2022-12-07/detail-imqqsmrp8860633.d.html",
            "title": "  【不按行政区域开展全员核酸检测】进一步优化核酸检测。不按行政区域开展全员核酸检测，进一步缩小核酸检测范围、减少频次。根据防疫工作需要，可开展抗原检测。对高风险岗位从业人员和高风险区人员按照有关规定进行核酸检测，其他人员愿检尽检。除养老院、福利院、医疗机构、托幼机构、中小学等特殊场所外，不要求提供核酸检测阴性证明，不查验健康码。重要机关、大型企业及一些特定场所可由属地自行确定防控措施。不再对跨地区流动人员查验核酸检测阴性证明和健康码，不再开展落地检。",
            "date_modified": "2022-12-07T05:30:29.000Z"
        },
        {
            "id": 2895637,
            "content_html": "",
            "url": "https://finance.sina.cn/7x24/2022-12-07/detail-imqqsmrp8859926.d.html",
            "title": "  日产汽车中国区11月销量为47983台，同比下降52.5%。",
            "date_modified": "2022-12-07T05:21:46.000Z"
        },
        {
            "id": 2895631,
            "content_html": "",
            "url": "https://finance.sina.cn/7x24/2022-12-07/detail-imqmmthc7321357.d.html",
            "title": "  【华南最大氢燃料电池供氢中心正式投用】12月7日，从中国石化新闻办获悉，近日，华南最大氢燃料电池供氢中心——中国石化茂名石化氢燃料电池供氢装置成功产出合格的99.999%高纯氢。该项目日产氢能力达6400公斤，每年可向社会供应高纯氢2100吨。",
            "date_modified": "2022-12-07T05:20:45.000Z"
        },
        {
            "id": 2895625,
            "content_html": "",
            "url": "https://finance.sina.cn/7x24/2022-12-07/detail-imqmmthc7321271.d.html",
            "title": "  【交通运输部：昨日全国高速公路货车通行718.51万辆 环比增长6.96%】据交通运输部12月7日消息，国务院物流保通保畅工作领导小组办公室监测汇总数据显示，12月6日，全国货运物流有序运行，其中：国家铁路货运继续保持高位运行，运输货物1099.9万吨，环比增长0.56%；全国高速公路货车通行718.51万辆，环比增长6.96%；监测港口完成货物吞吐量3335.2万吨，环比下降3.1%，完成集装箱吞吐量74.3万TEU，环比下降4.5%；民航保障货运航班633班（其中国际货运航班485班，国内货运航班148班），环比增长36.7%；邮政快递揽收量约3.68亿件，环比增长9.2%；投递量约3.00亿件，环比增长2.0%。截至12月6日24时，各省（区、市）高速公路无临时关闭收费站；共关停服务区37个，关停占比0.56%。",
            "date_modified": "2022-12-07T05:20:12.000Z"
        },
        {
            "id": 2895605,
            "content_html": "",
            "url": "https://finance.sina.cn/7x24/2022-12-07/detail-imqqsmrp8859521.d.html",
            "title": "【东鹏控股：加大营销渠道建设 前三季度新零售累计派单规模增长91.48%】东鹏控股近期接受机构调研时表示，电商渠道是重要的流量入口，东鹏的新零售业务在瓷砖行业历来名列前茅。公司继续加大品牌建设及营销渠道建设，前三季度新零售累计派单规模增长91.48%，线下成交率、客单值持续提升。",
            "date_modified": "2022-12-07T05:16:52.000Z"
        },
        {
            "id": 2895604,
            "content_html": "",
            "url": "https://finance.sina.cn/7x24/2022-12-07/detail-imqmmthc7321056.d.html",
            "title": "【中方坚决反对将粮食能源问题政治化工具化和武器化】中国常驻联合国副代表耿爽6日在安理会审议乌克兰人道问题时表示，中方坚决反对将粮食、能源问题政治化、工具化、武器化，同时呼吁国际社会向乌克兰民众提供过冬物资和取暖设备。耿爽表示，当前全球面临的粮食、能源危机不是生产和需求问题，而是供应链出了问题，国际合作受到干扰。他呼吁撤销单边制裁措施，维护全球经济复苏势头，减少发展中国家落实2030年可持续发展议程受到的冲击。（新华网）",
            "date_modified": "2022-12-07T05:16:30.000Z"
        },
        {
            "id": 2895583,
            "content_html": "",
            "url": "https://finance.sina.cn/7x24/2022-12-07/detail-imqmmthc7320639.d.html",
            "title": "【北向资金净流入超30亿元】按余额规模口径统计，截至目前北向资金净流入超30亿元，其中沪股通净流入10.1亿元，深股通净流入20.07亿元。",
            "date_modified": "2022-12-07T05:11:43.000Z"
        },
        {
            "id": 2895579,
            "content_html": "",
            "title": "A股三大指数悉数翻红，沪指午后拉升翻红，深证成指张0.6%，创业板指涨超1.3%。",
            "date_modified": "2022-12-07T05:10:15.000Z"
        },
        {
            "id": 2895577,
            "content_html": "",
            "url": "https://finance.sina.cn/7x24/2022-12-07/detail-imqmmthc7320246.d.html",
            "title": "沪指午后拉升翻红，创业板指涨超1.3%。",
            "date_modified": "2022-12-07T05:08:41.000Z"
        },
        {
            "id": 2895576,
            "content_html": "",
            "title": "【上海临港新片区：新能源智能汽车产值规模将达2400亿元】 据“上海临港”微信公众号，近日，2022第四届智能座舱与用户体验大会在上海举行。据悉，作为上海经济增长的发动机和新引擎，临港新片区将成为中国汽车电子和软件产业的自主创新集聚地，目前，临港新片区已集聚新能源智能汽车相关企业170多家，2021年的产值规模1794亿元，2022年将达到2400亿元。",
            "date_modified": "2022-12-07T05:08:33.000Z"
        },
        {
            "id": 2895543,
            "content_html": "",
            "title": "日本10月同步指标月率初值 -0.9%，前值-0.7%。日本10月领先指标月率初值 0.8%，前值-3.8%。日本10月领先指标初值 99，预期98.3，前值97.5。",
            "date_modified": "2022-12-07T05:00:35.000Z"
        },
        {
            "id": 2895536,
            "content_html": "",
            "url": "https://finance.sina.cn/7x24/2022-12-07/detail-imqmmthc7319288.d.html",
            "title": "\n【部分涉事企业有望脱离美方“未经核实清单”】据中国证券报，相关政府机构正在协助被美方列入“未经核实清单”的中国企业脱离清单。“被列入‘未经核实清单’后，我们一直在通过政府跟美方做沟通，美方核查完后会出具一份报告，然后决定是否排除。我们在等最后确认。”一家被列“未经核实清单”的企业有关负责人表示，“至于哪些企业获得协助，以及进展如何，等看结果。”",
            "date_modified": "2022-12-07T04:59:11.000Z"
        },
        {
            "id": 2895515,
            "content_html": "",
            "url": "https://finance.sina.cn/7x24/2022-12-07/detail-imqmmthc7318701.d.html",
            "title": "印度央行行长Das称，未来4个月通胀可能仍高于4%的目标水平。将印度2023财年GDP增速预期从7%下调至6.8%。",
            "date_modified": "2022-12-07T04:50:53.000Z"
        },
        {
            "id": 2895478,
            "content_html": "",
            "url": "https://finance.sina.cn/7x24/2022-12-07/detail-imqqsmrp8856623.d.html",
            "title": "【苹果放弃L5自动驾驶汽车 后期可能将降低对自动驾驶汽车的预期】据CNMO了解，苹果(AAPL.O)已经改变了未来推出“L5级”全自动驾驶汽车的想法，并将该汽车的目标推出日期推迟了约一年，至2026年。此外还有知情人士表示，苹果公司在后续的计划中，可能将降低对自动驾驶汽车的预期。苹果将生产一款含有方向盘和踏板，只支持高速公路上的完全自动驾驶功能的汽车。而这与苹果最初的愿景——“L5级”自动驾驶有着极大的差别。不过，L5级自动驾驶技术是无人驾驶技术的顶峰，到目前为止没有任何汽车制造商能够企及。",
            "date_modified": "2022-12-07T04:43:33.000Z"
        },
        {
            "id": 2895463,
            "content_html": "",
            "url": "https://finance.sina.cn/7x24/2022-12-07/detail-imqqsmrp8856433.d.html",
            "title": "  【新华制药：新达制药已取得治疗胆固醇型胆结石药物熊去氧胆酸片上市许可持有人资格】新华制药在互动平台表示，公司全资子公司新达制药已经取得治疗胆固醇型胆结石药物熊去氧胆酸片上市许可持有人资格。",
            "date_modified": "2022-12-07T04:41:15.000Z"
        },
        {
            "id": 2895456,
            "content_html": "",
            "url": "https://finance.sina.cn/7x24/2022-12-07/detail-imqmmthc7317680.d.html",
            "title": "  【广和通：正式发布5G智能模组SC171L】据广和通消息，2022年12月，广和通正式宣布：5G智能模组高性能SC171L发布，为对视频分辨率、多种接口连接有要求的工业手持、智能机器人、视频监控、车载后装、智慧零售终端等智能设备提供无线通信，助力全球5G AIoT产业发展。",
            "date_modified": "2022-12-07T04:39:46.000Z"
        },
        {
            "id": 2895449,
            "content_html": "",
            "title": "印度央行行长沙克蒂坎塔·达斯：全球经济受到严重冲击和不确定性的损害。通货膨胀仍然高企且广泛。全球食品和能源价格最近有所放缓。",
            "date_modified": "2022-12-07T04:35:44.000Z"
        },
        {
            "id": 2895425,
            "content_html": "",
            "url": "https://finance.sina.cn/7x24/2022-12-07/detail-imqqsmrp8855504.d.html",
            "title": "【华森制药：甘桔冰梅片为独家中药品种 可缓解因感冒引起的咳嗽等症状】华森制药在互动平台表示，公司生产的甘桔冰梅片为独家中药品种、国家中药保护品种，国家医保品种咽喉类专用药，尤其对急慢性咽炎、急慢性喉炎、急性扁桃体炎、声带小结、声带息肉、反流性咽喉炎等疗效突出，市场占有率高，是《中医耳鼻喉科临床诊疗指南》与《中成药临床应用指南·耳鼻咽喉疾病分册》等多个指南共识推荐用药，可缓解因感冒引起的咳嗽、咽痛、咽干灼热等症状。",
            "date_modified": "2022-12-07T04:30:08.000Z"
        },
        {
            "id": 2895424,
            "content_html": "",
            "url": "https://finance.sina.cn/7x24/2022-12-07/detail-imqmmthc7316889.d.html",
            "title": "市场消息， 特斯拉在泰国开放电动汽车预订。特斯拉将于明年第一季度开始在泰国交付电动汽车。",
            "date_modified": "2022-12-07T04:29:17.000Z"
        },
        {
            "id": 2895398,
            "content_html": "",
            "url": "https://finance.sina.cn/7x24/2022-12-07/detail-imqmmthc7316388.d.html",
            "title": "【集度汽车公司更名为上海幂航汽车】天眼查App显示，12月5日，集度汽车有限公司发生工商变更，企业名称变更为上海幂航汽车有限公司。该公司成立于2021年3月，注册资本20亿元人民币，法定代表人为梁志祥，由达孜县百瑞翔创业投资管理有限责任公司全资持股，李彦宏为疑似实际控制人。",
            "date_modified": "2022-12-07T04:22:39.000Z"
        },
        {
            "id": 2895397,
            "content_html": "",
            "url": "https://finance.sina.cn/7x24/2022-12-07/detail-imqqsmrp8854818.d.html",
            "title": "  【TrendForce：估未来三年全球军用无人机市场年复合增长率达27.6%】据TrendForce研究，随着各国积极投入军用无人机采购、部署与研发，预估2022年-2025年全球军用无人机市场规模有望自165亿美元成长至343亿美元，年复合增长率达27.6%。TrendForce补充，军用无人机不仅能发挥强大的不对称战力，其战备、整备、出击所需时间，也比传统打击武器如战机、坦克更少，而滞空时间更数倍于一般战机。",
            "date_modified": "2022-12-07T04:21:42.000Z"
        },
        {
            "id": 2895396,
            "content_html": "",
            "url": "https://finance.sina.cn/7x24/2022-12-07/detail-imqmmthc7316026.d.html",
            "title": "【集邦咨询：第三季智能手机总产量约2.89亿支 同比减少11%】据TrendForce集邦咨询研究显示，第三季全球智能手机总产量达2.89亿支，环比减少0.9%，同比减少11%，打破历年来第三季旺季正成长的规律，显示市况极为萎靡。主因是智能手机品牌厂在优先调节渠道成品库存的考量下，对于第三季的生产规划相当保守，加上全球经济疲软冲击，品牌持续下调生产目标所致。",
            "date_modified": "2022-12-07T04:19:45.000Z"
        },
        {
            "id": 2895395,
            "content_html": "",
            "url": "https://finance.sina.cn/7x24/2022-12-07/detail-imqmmthc7316005.d.html",
            "title": "【上海临港新片区：新能源智能汽车产值规模将达2400亿元】 “上海临港”微信公众号12月7日消息，第四届智能座舱与用户体验大会近日在上海举行。上海临港新片区目前已集聚新能源智能汽车相关企业170多家，2021年的产值规模1794亿元，2022年将达到2400亿元。依托《上海市浦东新区促进无驾驶人智能网联汽车创新应用规定》的实施以及同济大学为临港新片区量身打造的智慧交通顶层设计，上海临港将建设国内首个集“港口集卡、无人小巴、无人出租、智能公交”等为一体的全业态场景，建设国内首个集“软件在环、硬件在环、整车在环、封闭道路、公开道路”等为一体的全技术测试场景。",
            "date_modified": "2022-12-07T04:19:30.000Z"
        },
        {
            "id": 2895394,
            "content_html": "",
            "title": "【午间公告：晓鸣股份11月鸡产品销售收入同比增30%；七彩化学签署意向投资协议】①晓鸣股份：公司11月销售鸡产品1808.94万羽，销售收入6348.38万元，环比变动分别为-1.65%、0.87%，同比变动分别为18.76%、29.89%。②七彩化学：公司签署意向投资协议，拟和悦达汽车基金、吴中金控基金共同投资“苏州悦钠新能源科技有限公司”。本次签署意向投资协议，是基于公司未来在新能源电池产业中，特别是钠离子电池产业重要布局，实现钠离子电池正极材料层状氧化物、普鲁士蓝（白）双技术路线布局，产业链上下游互相促进，有利于强化与美联新材的战略合作，有利于公司快速进入钠离子电池正极材料主流技术和钠离子电池电芯制造领域。③双星新材：公司股东吴迪通过大宗交易、集中竞价的方式累计减持公司股票1260万股，占公司总股本的1.09%，已完成本次股份减持计划。",
            "date_modified": "2022-12-07T04:17:46.000Z"
        },
        {
            "id": 2895393,
            "content_html": "",
            "title": "  【国际奥委会推迟2030年冬奥会举办地选举】国际奥委会6日宣布，鉴于气候变化及其对冬季项目的影响，他们将打破常规、不在赛前七年宣布2030年冬奥会举办地。在国际奥委会执委会第二天的会议上，国际奥委会委员奥克塔维安·莫拉留做了详细的汇报。在该报告的建议下，国际奥委会执委会决定给予未来冬奥会举办地委员会更多时间来评估各种因素，从而选出最适合的冬奥会举办地。这也意味着国际奥委会将不会在原计划的2023年第140次全会上选出2030年冬奥会举办地。",
            "date_modified": "2022-12-07T04:13:58.000Z"
        },
        {
            "id": 2895392,
            "content_html": "",
            "url": "https://finance.sina.cn/7x24/2022-12-07/detail-imqqsmrp8854036.d.html",
            "title": "【网传杭州萧山区一医院在建方舱，医院：为改造期临时过渡门诊】 针对近期网上流传的一则“杭州萧山区一医院在建方舱”的消息，12月6日晚，消息中提及的杭州市萧山区第一人民医院通过微信视频号发布辟谣声明称，网传图为医院西面生态停车场改造的临时门诊部。该院称，为改善医院门诊环境，为市民提供更舒适、便利的诊疗环境，萧山区第一人民医院自11月3日起启动门诊改造工程，期间将医院西面生态停车场改造为临时门诊部。（澎湃新闻）",
            "date_modified": "2022-12-07T04:13:39.000Z"
        },
        {
            "id": 2895384,
            "content_html": "",
            "url": "https://finance.sina.cn/7x24/2022-12-07/detail-imqqsmrp8853089.d.html",
            "title": "【征求对经济工作的意见和建议 中共中央召开党外人士座谈会】央视新闻消息，中共中央在中南海召开党外人士座谈会，就今年经济形势和明年经济工作听取各民主党派中央、全国工商联负责人和无党派人士代表的意见和建议。",
            "date_modified": "2022-12-07T04:05:51.000Z"
        },
        {
            "id": 2895358,
            "content_html": "",
            "title": "【中俄东线天然气管道泰安至泰兴段正式投产】 中俄东线天然气管道泰安至泰兴段今天（7日）投产，我国由北向南的中俄东线天然气管道与由西向东的西气东输管道系统在江苏泰兴正式联通，来自西伯利亚的清洁能源全面供应长三角地区。（央视新闻）",
            "date_modified": "2022-12-07T03:57:46.000Z"
        },
        {
            "id": 2895336,
            "content_html": "",
            "url": "https://finance.sina.cn/7x24/2022-12-07/detail-imqqsmrp8851986.d.html",
            "title": "日本5年期国债收益率上涨0.5个基点，至0.135%，为10月24日以来新高。",
            "date_modified": "2022-12-07T03:54:14.000Z"
        },
        {
            "id": 2895315,
            "content_html": "",
            "url": "https://finance.sina.cn/7x24/2022-12-07/detail-imqqsmrp8851500.d.html",
            "title": "\n【华菱钢铁：根据下游订单需求和盈利情况调整生产节奏】华菱钢铁在机构调研时表示，下半年以来，受需求转弱影响，钢铁行业自发性减产。目前国家对钢铁行业实行产能、产量“双控”的产业政策，公司将积极响应国家号召，依法合规组织生产，并根据下游订单需求和盈利情况来调整生产节奏。",
            "date_modified": "2022-12-07T03:50:26.000Z"
        },
        {
            "id": 2895314,
            "content_html": "",
            "url": "https://finance.sina.cn/7x24/2022-12-07/detail-imqmmthc7312870.d.html",
            "title": "\n【《安徽省碳达峰实施方案》印发 到2025年非化石能源消费比重达到15.5%以上】据安徽发布消息，近日，安徽省人民政府发布通知，印发《安徽省碳达峰实施方案》。方案提出，到2025年，非化石能源消费比重达到15.5%以上，单位地区生产总值能耗比2020年下降14%，单位地区生产总值二氧化碳排放降幅完成国家下达目标；到2030年，非化石能源消费比重达到22%以上，单位地区生产总值二氧化碳排放比2005年下降65%以上，顺利实现2030年前碳达峰目标。",
            "date_modified": "2022-12-07T03:50:18.000Z"
        },
        {
            "id": 2895303,
            "content_html": "",
            "url": "https://finance.sina.cn/7x24/2022-12-07/detail-imqqsmrp8850968.d.html",
            "title": "\n【新华制药：公司尚无扑热息痛原料药生产】新华制药在互动平台表示，公司尚无扑热息痛原料药生产。",
            "date_modified": "2022-12-07T03:45:56.000Z"
        },
        {
            "id": 2895302,
            "content_html": "",
            "url": "https://finance.sina.cn/7x24/2022-12-07/detail-imqmmthc7312323.d.html",
            "title": "【索尼拟成立AI研究部门 带动游戏业务和创新】据报道，索尼12月6日透露，拟设立旨在提升AI功能的研究部门“Sony Research”，计划明年4月以后成立。此举意在获得新人才，开发利用AI的大规模模型，未来带动游戏等娱乐业务和创造新业务。索尼还表示，将在今后的研发中致力于AI、数字虚拟空间、半导体业务这三个领域。",
            "date_modified": "2022-12-07T03:45:37.000Z"
        },
        {
            "id": 2895300,
            "content_html": "",
            "url": "https://finance.sina.cn/7x24/2022-12-07/detail-imqmmthc7312252.d.html",
            "title": "泰国商务部：泰国12月份的通胀率可能与11月份持平。",
            "date_modified": "2022-12-07T03:44:55.000Z"
        },
        {
            "id": 2895258,
            "content_html": "",
            "url": "https://finance.sina.cn/7x24/2022-12-07/detail-imqqsmrp8849954.d.html",
            "title": "【元旦假日安排公布，机票、酒店搜索量分别上涨5倍、7倍】12月7日，据国务院办公室信息，2023年元旦放假时间从2022年12月31日至2023年1月2日，共3天。元旦放假日期确定后，同程旅行数据显示，截至当天上午10点，元旦期间出行的机票搜索量较前日同一时段上涨超过5倍，元旦期间的酒店搜索量较前日同一时间上涨近7倍。（澎湃新闻）",
            "date_modified": "2022-12-07T03:37:42.000Z"
        },
        {
            "id": 2895257,
            "content_html": "",
            "url": "https://finance.sina.cn/7x24/2022-12-07/detail-imqqsmrp8849898.d.html",
            "title": "\n【美媒：民主党候选人沃诺克赢得佐治亚州参议员席位】据央视新闻，当地时间12月6日，根据多家美媒预测，美国民主党佐治亚州参议员候选人沃诺克击败共和党候选人沃尔克，赢得参议院席位。沃诺克和沃尔克的票数一直非常接近。在开票95%后，沃诺克以50.4%比49.6%领先，两者依然仅相差不到3万票。至此，民主党在参议院共计获得51票，完全取得参议院的控制权。该结果比民主党2020年选举后多出一席。",
            "date_modified": "2022-12-07T03:37:25.000Z"
        },
        {
            "id": 2895231,
            "content_html": "",
            "url": "https://finance.sina.cn/7x24/2022-12-07/detail-imqqsmrp8849000.d.html",
            "title": "【龙净环保成立两家储能公司，注册资本均为5亿元】企查查APP显示，近日，福建龙净储能技术有限公司、福建龙净储能电池有限公司成立，注册资本皆为5亿元人民币，经营范围均包含：电池制造；储能技术服务；新材料技术研发；电池零配件生产、销售等。企查查股权穿透显示，二者皆由福建龙净环保股份有限公司关联公司控股。",
            "date_modified": "2022-12-07T03:30:10.000Z"
        },
        {
            "id": 2895223,
            "content_html": "",
            "title": "据中国海事局网站消息，葫芦岛海事局发布航行警告，12月7日10时至13时，渤海北部部分海域进行军事演习，禁止驶入。",
            "date_modified": "2022-12-07T03:29:08.000Z"
        },
        {
            "id": 2895194,
            "content_html": "",
            "url": "https://finance.sina.cn/7x24/2022-12-07/detail-imqqsmrp8848006.d.html",
            "title": "【中药股持续走强 贵州三力涨停】上海凯宝涨超10%，贵州三力涨停，仁和药业、贵州百灵、紫鑫药业、以岭药业、香雪制药、太极集团等跟涨。",
            "date_modified": "2022-12-07T03:20:57.000Z"
        },
        {
            "id": 2895173,
            "content_html": "",
            "title": "中国11月铁矿砂及其精矿进口9,884.6万吨。中国11月未锻轧铜及铜材进口539,901.7吨。中国11月煤及褐煤进口3,231.3万吨。中国11月原油进口4,674.0万吨。中国11月成品油进口310.1万吨。中国11月天然气进口1,031.6万吨。",
            "date_modified": "2022-12-07T03:14:42.000Z"
        },
        {
            "id": 2895167,
            "content_html": "",
            "title": "油气板块震荡走低，华锦股份跌超9%，中国海油、新潮能源、上海石化、贝肯能源、石化机械等跟跌。",
            "date_modified": "2022-12-07T03:11:49.000Z"
        }
    ]
}