{
    "version": "https://jsonfeed.org/version/1",
    "title": "新浪新闻",
    "home_page_url": "https://h52e5.github.io/sina-news/",
    "feed_url": "https://h52e5.github.io/sina-news/rss.json",
    "description": "新浪全球实时财经新闻",
    "items": [
        {
            "id": 2807117,
            "content_html": "",
            "title": "贝莱德：实施能源价格上限或将扭曲正常的需求反应。",
            "date_modified": "2022-09-20T09:13:29.000Z"
        },
        {
            "id": 2807116,
            "content_html": "",
            "url": "https://finance.sina.cn/7x24/2022-09-20/detail-imqmmtha8057738.d.html",
            "title": "【迦南科技：控股股东及非自然人股东拟减持不超过4%】迦南科技公告，控股股东及非自然人股东拟减持不超过4%。",
            "date_modified": "2022-09-20T09:13:08.000Z"
        },
        {
            "id": 2807114,
            "content_html": "",
            "url": "https://finance.sina.cn/7x24/2022-09-20/detail-imqqsmrn9816549.d.html",
            "title": "【香港金管局：为将来可能推出“数码港元”做准备】香港金融管理局今日发表题为《“数码港元”—迈出新一步》的政策立场文件，阐述金管局对零售层面央行数码货币（即“数码港元”或e-HKD）的政策立场及未来发展路向。金管局“金融科技2025”策略的其中一个方向，是加强对央行数码货币的研究工作，让香港能作出充分准备。金管局已从技术及政策层面审视在香港发行“数码港元”的可行性，并分别就高层次技术设计及主要政策与设计事项进行了两轮市场咨询。",
            "date_modified": "2022-09-20T09:12:24.000Z"
        },
        {
            "id": 2807111,
            "content_html": "",
            "url": "https://finance.sina.cn/7x24/2022-09-20/detail-imqmmtha8057248.d.html",
            "title": "【力量钻石：拟使用不超35亿元闲置募集资金进行现金管理】力量钻石(301071)9月20日晚间公告，公司拟使用不超过35亿元闲置募集资金进行现金管理，拟投资的产品品种包括期限不超过12个月的保本型理财产品、结构性存款和定期存款。",
            "date_modified": "2022-09-20T09:10:44.000Z"
        },
        {
            "id": 2807110,
            "content_html": "",
            "title": "【GIC Private Limited对中国中免的持股比例从10.01%降至9.94%】据港交所披露文件，GIC Private Limited于9月15日减持中国中免6.5万股H股，持股比例从10.01%降至9.94%。",
            "date_modified": "2022-09-20T09:09:40.000Z"
        },
        {
            "id": 2807109,
            "content_html": "",
            "url": "https://finance.sina.cn/7x24/2022-09-20/detail-imqmmtha8056946.d.html",
            "title": "【欣旺达：拟213亿元投建义乌新能源动力电池项目】欣旺达(300207)9月20日晚间公告，子公司欣旺达汽车电池拟与义乌市人民政府签署《项目投资协议书》。该项目投资主要从事锂离子动力电池及储能电池等产品的生产和销售，产品涵盖汽车动力电池和储能电池的电芯、模组、PACK及电池系统等。该项目计划总投入约213亿元，其中固定资产投资约160亿元，计划建设动力电池及储能电池总产能约50GWh生产基地。",
            "date_modified": "2022-09-20T09:09:21.000Z"
        },
        {
            "id": 2807108,
            "content_html": "",
            "url": "https://finance.sina.cn/7x24/2022-09-20/detail-imqmmtha8056917.d.html",
            "title": "马来西亚9月1日至20日棕榈油出口量环比增长30.58％。",
            "date_modified": "2022-09-20T09:09:02.000Z"
        },
        {
            "id": 2807106,
            "content_html": "",
            "url": "https://finance.sina.cn/7x24/2022-09-20/detail-imqqsmrn9815722.d.html",
            "title": "罗曼股份：上海诚毅拟减持不超过1.85%。",
            "date_modified": "2022-09-20T09:08:08.000Z"
        },
        {
            "id": 2807105,
            "content_html": "",
            "title": "【极端天气导致韩国蔬菜大幅减产价格暴涨 中国产泡菜成救兵】受罕见高温、暴雨、台风等极端天气影响，近来韩国蔬菜大幅减产，价格暴涨，韩国农林畜产食品部表示，9月11日至19日，首尔可乐市场一颗白菜的批发价高达8992韩元，比本月1日至10日上涨了28%。韩国泡菜价格涨不停，相对价格低廉的中国产泡菜进口量持续增长，韩国关税厅进出口贸易统计显示，今年前8个月，韩国进口中国产泡菜累计1.986亿美元（约合13.9亿元人民币），同比增长27.6%。尤其是8月单月泡菜进口额达1337.6万美元（约合9381万元人民币），同比大增41.1%，关税厅预计中国产泡菜进口将持续增长。",
            "date_modified": "2022-09-20T09:07:44.000Z"
        },
        {
            "id": 2807104,
            "content_html": "",
            "url": "https://finance.sina.cn/7x24/2022-09-20/detail-imqmmtha8056508.d.html",
            "title": "【晶科科技与郴电国际、苏文电能签订75MW/150MWH集中式共享储能合作协议】9月15日，晶科科技与郴电国际、苏文电能正式签署《75MW/150MWH集中式共享储能项目合作框架协议》。根据协议，三方将共同布局郴州储能项目建设，推动光储能源一体化发展，为地区低碳转型，绿能发展添力赋能。",
            "date_modified": "2022-09-20T09:06:23.000Z"
        },
        {
            "id": 2807103,
            "content_html": "",
            "url": "https://finance.sina.cn/7x24/2022-09-20/detail-imqmmtha8056129.d.html",
            "title": "波音(BA.N)盘前拉升转涨。",
            "date_modified": "2022-09-20T09:04:00.000Z"
        },
        {
            "id": 2807102,
            "content_html": "",
            "url": "https://finance.sina.cn/7x24/2022-09-20/detail-imqqsmrn9814702.d.html",
            "title": "【中国民航恢复737MAX新飞机引进即将完成全部流程】9月14日，民航局与波音公司在浙江舟山组织召开了737MAX飞机运行评审（即AEG评审）专题会议，旨在评审737系列改进后的整体机型训练规范。据悉，预期会议提出的疑问解决后，民航局将发布《波音737系列飞机航空器评审报告》第二次修订，标志着中国民航恢复737MAX新飞机引进即将完成全部流程。（中国民航报）",
            "date_modified": "2022-09-20T09:02:20.000Z"
        },
        {
            "id": 2807101,
            "content_html": "",
            "title": "广发证券：中国证监会同意公司向专业投资者公开发行面值总额不超过100亿元次级公司债券的注册申请。该批复自同意注册之日起24个月内有效。",
            "date_modified": "2022-09-20T09:00:44.000Z"
        },
        {
            "id": 2807100,
            "content_html": "",
            "url": "https://finance.sina.cn/7x24/2022-09-20/detail-imqmmtha8055347.d.html",
            "title": "【匈牙利外长：欧盟不应再对俄施加制裁】当地时间9月20日，匈牙利外交部长西雅尔多表示，欧盟不应该再向俄罗斯施加制裁。他表示，施加新的制裁只能加剧欧洲的能源危机，损害欧洲自身。俄乌冲突爆发以来，欧盟与美国一道对俄罗斯施加多轮制裁，但由于不少欧盟国家长期依赖俄罗斯能源供应，其反噬作用令欧盟处境窘迫。（央视新闻）",
            "date_modified": "2022-09-20T09:00:07.000Z"
        },
        {
            "id": 2807099,
            "content_html": "",
            "url": "https://finance.sina.cn/7x24/2022-09-20/detail-imqmmtha8055196.d.html",
            "title": "【思进智能：股东拟继续减持公司不超3.8%股份】思进智能9月20日晚间公告，股东宁波富博睿祺创业投资中心（有限合伙）累计减持公司股份309.22万股，占公司总股本的2.0533%。此次减持完成后，富博睿祺尚持有公司股份1481.15万股，占公司总股本的9.0761%。富博睿祺计划以集中竞价交易或大宗交易方式继续减持公司股份累计不超过620万股（占公司总股本比例3.7992%）。",
            "date_modified": "2022-09-20T08:59:15.000Z"
        },
        {
            "id": 2807098,
            "content_html": "",
            "url": "https://finance.sina.cn/7x24/2022-09-20/detail-imqqsmrn9813876.d.html",
            "title": "【百宏实业：投资5.18亿元用于扩产越南30万吨聚酯瓶片项目】百宏实业公告，将进一步在越南投资7390万美元(约合人民币5.18亿元)扩产聚酯瓶片产线。包括购买20万平米的土地，建设1.4万平米的新厂房，预计新增产能为30万吨。",
            "date_modified": "2022-09-20T08:57:52.000Z"
        },
        {
            "id": 2807096,
            "content_html": "",
            "title": "贝壳(BEKE.N)：于9月19日回购50.2万股，回购价格为5.86-6.01美元，共耗资约300万美元。",
            "date_modified": "2022-09-20T08:57:03.000Z"
        },
        {
            "id": 2807095,
            "content_html": "",
            "url": "https://finance.sina.cn/7x24/2022-09-20/detail-imqqsmrn9813701.d.html",
            "title": "【德尔股份：控股股东之一致行动人拟减持不超过1.79%】德尔股份公告，控股股东之一致行动人拟减持不超过1.793%。",
            "date_modified": "2022-09-20T08:56:40.000Z"
        },
        {
            "id": 2807094,
            "content_html": "",
            "url": "https://finance.sina.cn/7x24/2022-09-20/detail-imqqsmrn9813679.d.html",
            "title": "【海波重科：与金智科技签订战略合作协议】海波重科公告，与江苏金智科技股份有限公司签订战略合作协议，在光伏建设一体化、储能等新能源领域，双方根据具体项目情况将以共同投资成立项目公司等多种形式进一步深化合作。",
            "date_modified": "2022-09-20T08:56:27.000Z"
        },
        {
            "id": 2807093,
            "content_html": "",
            "url": "https://finance.sina.cn/7x24/2022-09-20/detail-imqqsmrn9813625.d.html",
            "title": "欧洲央行管委穆勒：现在必须对抗通胀，否则以后就必须大幅加息。需要“足够强大、果断的”政策措施。",
            "date_modified": "2022-09-20T08:55:57.000Z"
        },
        {
            "id": 2807092,
            "content_html": "",
            "title": "美国国家飓风中心：飓风“菲奥娜”造成多米尼加共和国东部地区仍在发生强降雨和危及生命的暴洪。",
            "date_modified": "2022-09-20T08:55:25.000Z"
        },
        {
            "id": 2807091,
            "content_html": "",
            "url": "https://finance.sina.cn/7x24/2022-09-20/detail-imqqsmrn9813536.d.html",
            "title": "【国信证券现4.17亿元溢价大宗交易 机构卖出】国信证券今日收跌0.34%，报8.83元。该股当日出现4.17亿元溢价大宗交易，成交价为8.86元/股，买方为中信证券北京总部证券营业部，卖方为机构专用席位。",
            "date_modified": "2022-09-20T08:55:07.000Z"
        },
        {
            "id": 2807090,
            "content_html": "",
            "url": "https://finance.sina.cn/7x24/2022-09-20/detail-imqqsmrn9813128.d.html",
            "title": "【双汇发展现2.06亿元溢价大宗交易 机构卖出 】双汇发展今日收跌0.56%，报24.75元。该股当日出现2.06亿元溢价大宗交易，成交价为24.77元/股，买方为中信证券北京总部证券营业部，卖方为机构专用席位。",
            "date_modified": "2022-09-20T08:52:21.000Z"
        },
        {
            "id": 2807089,
            "content_html": "",
            "url": "https://finance.sina.cn/7x24/2022-09-20/detail-imqmmtha8053947.d.html",
            "title": "【上海启动清理规范行动 打击寄生在银行保险产业链上的不法中介】近期上海银保监局启动清理规范金融中介活动专项行动，旨在进一步规范清理辖内银行保险机构与各类中介的合作，防范相关风险向银行保险体系传导，发现和打击寄生在银行保险产业链上的不法中介，促进金融服务直达消费者。（上证报）",
            "date_modified": "2022-09-20T08:50:30.000Z"
        },
        {
            "id": 2807088,
            "content_html": "",
            "url": "https://finance.sina.cn/7x24/2022-09-20/detail-imqqsmrn9812611.d.html",
            "title": "【前8月青海省对“一带一路”沿线国家合计进出口增长1.4倍】今年前8个月，青海省进出口总值28.8亿元，增速高于全国46.7个百分点，其中对“一带一路”沿线国家合计进出口增长1.4倍。据西宁海关统计，2022年前8个月，青海省进出口总值增速排名全国第2位。据西宁海关负责人介绍，前8个月，青海省对“一带一路”沿线国家合计进出口10.3亿元，增长1.4倍，对RCEP成员国合计进出口11.2亿元，增长1.8倍；其中东盟、几内亚、日本、南非、新加坡为前五大贸易伙伴。 (中国新闻网)",
            "date_modified": "2022-09-20T08:49:38.000Z"
        },
        {
            "id": 2807087,
            "content_html": "",
            "title": "保加利亚天然气公司Bulgargaz CEO：保加利亚将于今日启动液化天然气项目招标。",
            "date_modified": "2022-09-20T08:48:38.000Z"
        },
        {
            "id": 2807086,
            "content_html": "",
            "url": "https://finance.sina.cn/7x24/2022-09-20/detail-imqqsmrn9812392.d.html",
            "title": "中国移动：移动业务8月净增客户数210.9万，本年累计净增客户数1,635万。",
            "date_modified": "2022-09-20T08:48:23.000Z"
        },
        {
            "id": 2807084,
            "content_html": "",
            "title": "穆巴达拉能源公司(Mubadala Energy）在马来西亚发现天然气储层。",
            "date_modified": "2022-09-20T08:45:43.000Z"
        },
        {
            "id": 2807083,
            "content_html": "",
            "title": "【王毅阐述中国自身发展和对美政策确定性】当地时间9月19日，国务委员兼外长王毅在纽约与美中关系全国委员会、美中贸易全国委员会、美国商会代表成员进行座谈交流。针对当前中美关系前景中的确定性越来越少，不确定性越来越多，王毅阐述了中国的五个“确定性”。王毅表示，中国自身的发展前景是确定的，中国改革开放的决心是确定的，中国对美政策是确定的，中国继续加强两国经贸合作的态度是确定的，中国同美方开展多边协调的意愿是确定的。王毅表示，必须维护好中美关系的政治基础，尤其是切实恪守一个中国原则。（央视新闻）",
            "date_modified": "2022-09-20T08:45:11.000Z"
        },
        {
            "id": 2807082,
            "content_html": "",
            "title": "中国地震台网正式测定：09月20日16时17分在墨西哥（北纬18.40度，西经103.55度）发生5.9级地震，震源深度10千米。",
            "date_modified": "2022-09-20T08:42:42.000Z"
        },
        {
            "id": 2807079,
            "content_html": "",
            "url": "https://finance.sina.cn/7x24/2022-09-20/detail-imqmmtha8051868.d.html",
            "title": "【日本全国住宅用地均价31年来首次同比上涨】当地时间9月20日，日本国土交通省发布的2022年基准地价统计数据显示，日本全国所有用地均价相比上一年上涨0.3%，为3年来首次出现正增长。其中，住宅用地均价较去年上涨0.1%，是1991年以来首次同比上涨。（央视新闻）",
            "date_modified": "2022-09-20T08:38:04.000Z"
        },
        {
            "id": 2807078,
            "content_html": "",
            "url": "https://finance.sina.cn/7x24/2022-09-20/detail-imqmmtha8051565.d.html",
            "title": "【公元股份：控股子公司新三板挂牌申请获受理】公元股份9月20日晚间公告，控股子公司浙江公元新能源科技股份有限公司在全国中小企业股份转让系统挂牌申请获得受理。",
            "date_modified": "2022-09-20T08:35:59.000Z"
        },
        {
            "id": 2807077,
            "content_html": "",
            "url": "https://finance.sina.cn/7x24/2022-09-20/detail-imqmmtha8051506.d.html",
            "title": "天源环保：中标2.5亿元获嘉县生活垃圾焚烧发电建设项目。",
            "date_modified": "2022-09-20T08:35:24.000Z"
        },
        {
            "id": 2807076,
            "content_html": "",
            "url": "https://finance.sina.cn/7x24/2022-09-20/detail-imqmmtha8051340.d.html",
            "title": "普洛药业：吸入用乙酰半胱氨酸溶液获得药品注册证书。",
            "date_modified": "2022-09-20T08:34:08.000Z"
        },
        {
            "id": 2807075,
            "content_html": "",
            "url": "https://finance.sina.cn/7x24/2022-09-20/detail-imqqsmrn9810130.d.html",
            "title": "【郑州第二批供地3宗地块终止出让，供地数量减至14宗】据新京报，9月20日，河南省郑州市公共资源交易中心官网显示，郑州市今年第二批集中供地计划中的3宗地块终止挂牌出让。至此，郑州市本批次集中供应土地数量减至14宗，总起始价约103.24亿元。",
            "date_modified": "2022-09-20T08:33:48.000Z"
        },
        {
            "id": 2807074,
            "content_html": "",
            "url": "https://finance.sina.cn/7x24/2022-09-20/detail-imqqsmrn9810102.d.html",
            "title": "【天津拟提高这些家庭首套房公积金贷款额度】9月20日，天津市住房公积金管理中心发布了“关于《关于调整租房提取住房公积金和个人住房公积金贷款有关政策的通知（征求意见稿）》公开征求意见的公告”。其中提到：养育未成年二孩及以上多子女的本市缴存职工，符合租房提取住房公积金条件的，可按照实际房租支出提取住房公积金；申请个人住房公积金贷款购买家庭首套住房的，贷款最高限额以本市统一贷款限额为基础上浮20%。（津云微信公号）",
            "date_modified": "2022-09-20T08:33:35.000Z"
        },
        {
            "id": 2807073,
            "content_html": "",
            "url": "https://finance.sina.cn/7x24/2022-09-20/detail-imqmmtha8051190.d.html",
            "title": "印度方面表示，针对斯里兰卡危机，印度将继续支持斯里兰卡，特别是通过促进长期投资。",
            "date_modified": "2022-09-20T08:33:04.000Z"
        },
        {
            "id": 2807072,
            "content_html": "",
            "url": "https://finance.sina.cn/7x24/2022-09-20/detail-imqqsmrn9809942.d.html",
            "title": "【百度糯米App将于12月停止服务 称因公司业务调整】百度糯米发布App下线公告称，因公司业务调整，百度糯米App将停止服务与运营，预计将于2022年12月正式停止相关服务。目前，百度糯米官网已无法访问用户个人数据，百度糯米App已在各主要应用商店下架。",
            "date_modified": "2022-09-20T08:32:32.000Z"
        },
        {
            "id": 2807071,
            "content_html": "",
            "url": "https://finance.sina.cn/7x24/2022-09-20/detail-imqqsmrn9809892.d.html",
            "title": "【上海临港：全资子公司拟以公开挂牌方式引入战略投资者】上海临港9月20日晚间公告，公司全资子公司高科技园公司拟通过公开挂牌方式增资扩股引入战略投资者，增资金额不超过30亿元。增资扩股完成后，公司持有高科技园公司的股权比例预计不低于84.38%，引入的战略投资者持股比例不高于15.62%，公司仍为高科技园公司的控股股东。",
            "date_modified": "2022-09-20T08:32:00.000Z"
        },
        {
            "id": 2807070,
            "content_html": "",
            "title": "欧洲央行管委穆勒：从历史上看，现在的利率水平仍然很低。利率远未达到能使经济放缓的限制性水平。",
            "date_modified": "2022-09-20T08:31:46.000Z"
        },
        {
            "id": 2807068,
            "content_html": "",
            "url": "https://finance.sina.cn/7x24/2022-09-20/detail-imqmmtha8050954.d.html",
            "title": "【汤加一火山48小时内喷发8次 当地提高预警级别至橙色】根据汤加地质服务局消息，汤加主岛以北一座火山在过去48小时内喷发了8次。当局提醒海员注意和火山保持距离。报道称，过去10天，该火山持续喷出熔岩，并形成大量火山灰。随着喷发速度加快，当地已将预警级别提高至橙色，飞行员在飞越火山附近空域时要小心。",
            "date_modified": "2022-09-20T08:31:17.000Z"
        },
        {
            "id": 2807067,
            "content_html": "",
            "url": "https://finance.sina.cn/7x24/2022-09-20/detail-imqmmtha8050894.d.html",
            "title": "【海峡环保：瑞力投资拟减持不超过1.31%】海峡环保公告，瑞力投资拟减持不超过1.31%。",
            "date_modified": "2022-09-20T08:30:58.000Z"
        },
        {
            "id": 2807066,
            "content_html": "",
            "url": "https://finance.sina.cn/7x24/2022-09-20/detail-imqmmtha8050821.d.html",
            "title": "【国信证券：上市证券做市交易业务资格获核准】国信证券公告，近日，公司收到中国证监会《关于核准国信证券股份有限公司上市证券做市交易业务资格的批复》，根据相关规定，中国证监会核准公司上市证券做市交易业务资格。",
            "date_modified": "2022-09-20T08:30:43.000Z"
        },
        {
            "id": 2807065,
            "content_html": "",
            "url": "https://finance.sina.cn/7x24/2022-09-20/detail-imqmmtha8050755.d.html",
            "title": "【中国宝安：石墨烯材料是贝特瑞的种子业务，尚处于培育阶段】中国宝安在投资者互动平台表示，石墨烯材料是贝特瑞的种子业务，尚处于培育阶段，目前暂未贡献业绩及利润。",
            "date_modified": "2022-09-20T08:30:26.000Z"
        },
        {
            "id": 2807064,
            "content_html": "",
            "url": "https://finance.sina.cn/7x24/2022-09-20/detail-imqqsmrn9809600.d.html",
            "title": "【五矿稀土：拟将证券简称变更为“中国稀土”】五矿稀土9月20日晚间公告，公司拟将名称由原“五矿稀土股份有限公司”变更为“中国稀土集团资源科技股份有限公司”，证券简称由“五矿稀土”变更为“中国稀土”。",
            "date_modified": "2022-09-20T08:30:09.000Z"
        },
        {
            "id": 2807062,
            "content_html": "",
            "url": "https://finance.sina.cn/7x24/2022-09-20/detail-imqqsmrn9809378.d.html",
            "title": "沙特阿美CEO：十年前就已经有明显的能源危机信号了。",
            "date_modified": "2022-09-20T08:28:28.000Z"
        },
        {
            "id": 2807061,
            "content_html": "",
            "url": "https://finance.sina.cn/7x24/2022-09-20/detail-imqqsmrn9809200.d.html",
            "title": "【丰元股份今日涨停 两机构净买入9044.95万元】丰元股份今日涨停，成交额9.18亿元，换手率13.18%，盘后龙虎榜数据显示，两机构净买入9044.95万元。",
            "date_modified": "2022-09-20T08:27:29.000Z"
        },
        {
            "id": 2807060,
            "content_html": "",
            "url": "https://finance.sina.cn/7x24/2022-09-20/detail-imqqsmrn9809176.d.html",
            "title": "欧洲地中海地震中心：墨西哥米却肯州发生5.6级地震。",
            "date_modified": "2022-09-20T08:27:13.000Z"
        },
        {
            "id": 2807059,
            "content_html": "",
            "url": "https://finance.sina.cn/7x24/2022-09-20/detail-imqmmtha8050174.d.html",
            "title": "【永安药业：与浙江双子签订不超过5000万元框架协议】永安药业9月20日晚间公告，目前，根据公司技术改造和项目建设需要，此前协议已不能满足公司实际需求，因此董事会决定加大与浙江双子智能装备有限公司的合作力度，重新与其签订交易总金额不超过5000万元的《设备制造及系统集成框架协议》，该协议签订后，原交易总金额不超过1000万元协议终止。",
            "date_modified": "2022-09-20T08:26:10.000Z"
        },
        {
            "id": 2807057,
            "content_html": "",
            "title": "【2022世界制造业大会在安徽合肥开幕】由工信部、科技部、商务部、国务院国资委、中国工程院、国务院发展研究中心、全国工商联、全国对外友协、中国中小企业协会、全球中小企业联盟、安徽省人民政府共同主办的2022世界制造业大会在安徽省合肥市开幕。本次大会以“制造世界 创造美好”为主题，紧扣制造业发展趋势和热点，旨在进一步凝聚各方共识，搭建促进制造业创新发展与交流合作平台。大会围绕新能源汽车、新一代信息技术、高端装备制造、新材料、智能家电等发布了15项重大创新产品，进行了央企、民企、外企、港澳企、台企、侨企“六百”项目签约，设置了平行论坛及展览展示、大会发布、线上展会等活动。",
            "date_modified": "2022-09-20T08:25:46.000Z"
        },
        {
            "id": 2807056,
            "content_html": "",
            "title": "【俄气：“西伯利亚力量”天然气管道将临时中断供气】当地时间9月20日，俄罗斯天然气工业股份公司发布消息说，“西伯利亚力量”天然气管道的天然气运输将于9月22日至29日期间暂停，原因是将进行管道维修工作。（央视新闻）",
            "date_modified": "2022-09-20T08:25:21.000Z"
        },
        {
            "id": 2807055,
            "content_html": "",
            "url": "https://finance.sina.cn/7x24/2022-09-20/detail-imqqsmrn9808919.d.html",
            "title": "【钧达股份今日涨停 两机构净买入1.24亿元】钧达股份今日涨停，成交额12.05亿元，换手率4.59%，盘后龙虎榜数据显示，两机构净买入1.24亿元，四机构净卖出1.15亿元。",
            "date_modified": "2022-09-20T08:25:00.000Z"
        },
        {
            "id": 2807053,
            "content_html": "",
            "url": "https://finance.sina.cn/7x24/2022-09-20/detail-imqqsmrn9808598.d.html",
            "title": "【匈牙利大部分加油站将在下周断油】据报道，从9月19日起，匈牙利天然气和石油巨头MOL只能提供所需燃料的四分之一。MOL解释说，油气供应短缺的原因是为了保持匈牙利燃料订单和供应的可预测性。这家油气巨头的声明也涉及汽油和柴油的交付。与其他欧洲国家一样，匈牙利政府决定在今年年底前维持燃料和基本食品的价格上限。匈牙利的汽油和柴油价格将保持在每升480匈牙利福林(1.19欧元/升)。这样做的代价是很快就没有汽油和柴油了。",
            "date_modified": "2022-09-20T08:22:27.000Z"
        },
        {
            "id": 2807052,
            "content_html": "",
            "url": "https://finance.sina.cn/7x24/2022-09-20/detail-imqqsmrn9808055.d.html",
            "title": "【优彩资源：上海凯峰拟减持不超过2%】优彩资源公告，上海凯峰拟减持不超过2%。",
            "date_modified": "2022-09-20T08:19:02.000Z"
        },
        {
            "id": 2807051,
            "content_html": "",
            "url": "https://finance.sina.cn/7x24/2022-09-20/detail-imqqsmrn9807953.d.html",
            "title": "【美迪凯：丰盛佳美拟减持不超过2%股份】美迪凯公告，丰盛佳美拟减持不超过2%股份。同日公告，拟将所持有智能光电4.1%股权和5.35%股权分别以322.85万元和421.27万元的对价转让给美迪凯一号、美迪凯二号。",
            "date_modified": "2022-09-20T08:18:36.000Z"
        },
        {
            "id": 2807050,
            "content_html": "",
            "url": "https://finance.sina.cn/7x24/2022-09-20/detail-imqqsmrn9807928.d.html",
            "title": "【三安光电股价跌逾7%，回应称网络传闻为假消息】9月20日，三安光电股价跌幅为7.05%。当日，有用户在网络平台发帖称，三安光电有相关人士中午在办公室被带走。对此，三安光电工作人员回应称，该传闻为假消息。（每日经济新闻）",
            "date_modified": "2022-09-20T08:18:12.000Z"
        },
        {
            "id": 2807048,
            "content_html": "",
            "title": "【艾比森：公司虚拟拍摄全场景LED显示解决方案已应用于全球主要国家的虚拟摄影棚等场景】艾比森在接受调研时表示，目前公司推出的虚拟拍摄全场景LED显示解决方案已成功应用于美国、中国、英国、法国、俄罗斯、加拿大等全球主要国家的虚拟摄影棚、演播室、XR舞台等场景，取得了良好的市场反馈，行业优势显著。",
            "date_modified": "2022-09-20T08:16:44.000Z"
        },
        {
            "id": 2807036,
            "content_html": "",
            "url": "https://finance.sina.cn/7x24/2022-09-20/detail-imqqsmrn9807108.d.html",
            "title": "今日0时至14时，西藏新增无症状感染者51例。（央视新闻）",
            "date_modified": "2022-09-20T08:11:43.000Z"
        },
        {
            "id": 2807033,
            "content_html": "",
            "url": "https://finance.sina.cn/7x24/2022-09-20/detail-imqmmtha8048084.d.html",
            "title": "【人福医药：氯巴占片获得药品注册证书】人福医药公告，氯巴占片获得药品注册证书。",
            "date_modified": "2022-09-20T08:11:09.000Z"
        },
        {
            "id": 2807032,
            "content_html": "",
            "title": "【韩电池商希望美国豁免从中国采购原材料】韩国电动汽车电池制造商希望美国对一项要求其在中国以外地区多元化采购的法律提供豁免。今年8月美国通过《通胀削减法案》法案，旨在提高美国国内电动汽车产量，减少对中国原材料的依赖。根据这部法律，电池制造商到2023年须从中国以外地区采购至少40%的矿物原材料，到2027年这一比例将升至80%。韩国的电池制造商中许多与特斯拉、通用汽车、福特汽车等美国汽车制造商有合作关系。根据韩国贸易部，当前该国电动汽车电池制造商58%的锂、64%的钴、70%的石墨来自中国。韩国电动汽车电池制造商金肯尼（音译自Kenny Kim）在首尔会议间隙上表示，如果美国关于《通胀削减法案》不对韩国电池制造商提供豁免或优待，这些企业可能难以满足严格的要求，或从2024年开始无法遵守。（财联社）",
            "date_modified": "2022-09-20T08:10:49.000Z"
        },
        {
            "id": 2807030,
            "content_html": "",
            "url": "https://finance.sina.cn/7x24/2022-09-20/detail-imqmmtha8047626.d.html",
            "title": "【长春高新回应“集采假消息做空事件”：已注意到股东维护合法权益】9月20日，针对“长春高新集采假消息做空事件”，长春高新表示，公司积极关注此事件，公司注意到部分股东通过合法渠道维护个人合法权益，但相关事实还需依靠监管机构查证，公司这边没有太多能回应的。(界面)",
            "date_modified": "2022-09-20T08:08:56.000Z"
        },
        {
            "id": 2807029,
            "content_html": "",
            "url": "https://finance.sina.cn/7x24/2022-09-20/detail-imqmmtha8047546.d.html",
            "title": "【有色协会锡业分会：8月锡精矿进口金属量下滑超40%】中国有色金属工业协会锡业分会发布的数据显示，根据中国海关数据以及安泰科的折算，2022年8月我国锡精矿进口实物量17227吨，折金属量3601.1吨，环比下滑41.2%，同比下滑1.4%。主要进口来源地中，来自东南亚、南美洲以及非洲的主要锡生产区的进口含锡量均呈现出下降趋势，仅澳洲进口量有所增长。截至2022年8月末，我国累计进口锡精矿4.6万吨金属量，同比增长63.4%。",
            "date_modified": "2022-09-20T08:08:25.000Z"
        },
        {
            "id": 2807028,
            "content_html": "",
            "title": "【黑龙江省人民检察院原党组成员、副厅级检察员董金山被开除党籍】据黑龙江省纪委监委消息：日前，经黑龙江省委批准，黑龙江省纪委监委对省人民检察院原党组成员、副厅级检察员董金山严重违纪违法问题进行了立案审查调查。经省纪委常委会会议研究并报省委批准，决定给予董金山开除党籍处分；按规定取消其享受的待遇；收缴其违纪违法所得；将其涉嫌犯罪问题移送检察机关依法审查起诉，所涉财物一并移送。",
            "date_modified": "2022-09-20T08:08:03.000Z"
        },
        {
            "id": 2807027,
            "content_html": "",
            "url": "https://finance.sina.cn/7x24/2022-09-20/detail-imqqsmrn9806385.d.html",
            "title": "【中国铁合金工业协会铬系专业委员会召开信息交流会议 强调实质性减产限产】中国铁合金工业协会铬系专业委员会9月20日召开信息沟通交流会议。会议对多数铬系合金生产企业通过减产限产、计划性检修、降低生产负荷等措施进而调整市场供需关系、强化行业自律、最大限度维持行业健康发展的做法给予充分肯定。会议强调，铬系合金行业面临严峻考验的根源在于供需错配，解决问题的落脚点还是要通过实质性减产限产来进一步有效调整供需关系。",
            "date_modified": "2022-09-20T08:07:50.000Z"
        },
        {
            "id": 2807025,
            "content_html": "",
            "title": "福特汽车盘前跌4.5%，公司表示，第三季度与通胀相关的供应商成本将比最初预期高出约10亿美元。",
            "date_modified": "2022-09-20T08:05:19.000Z"
        },
        {
            "id": 2807024,
            "content_html": "",
            "url": "https://finance.sina.cn/7x24/2022-09-20/detail-imqmmtha8046959.d.html",
            "title": "雾芯科技(RLX.N)盘前涨3.4%，将于明日美股盘前发布财报。",
            "date_modified": "2022-09-20T08:04:21.000Z"
        },
        {
            "id": 2807020,
            "content_html": "",
            "url": "https://finance.sina.cn/7x24/2022-09-20/detail-imqmmtha8046832.d.html",
            "title": "市场消息：欧洲投资银行不会资助天然气项目。",
            "date_modified": "2022-09-20T08:03:08.000Z"
        },
        {
            "id": 2807018,
            "content_html": "",
            "url": "https://finance.sina.cn/7x24/2022-09-20/detail-imqmmtha8046627.d.html",
            "title": "【日本航空自卫队和德国空军将首次在日进行共同训练】据日本广播协会报道，日本航空自卫队宣布，德国空军的3架战斗机将于本月28日飞抵茨城县百里基地，与日方3架F-2战斗机进行共同训练。这将是日本航空自卫队和德国空军首次在日本国内进行共同训练。（央视新闻）",
            "date_modified": "2022-09-20T08:01:45.000Z"
        },
        {
            "id": 2807016,
            "content_html": "",
            "url": "https://finance.sina.cn/7x24/2022-09-20/detail-imqqsmrn9805523.d.html",
            "title": "欧元区7月季调后经常帐逆差198.59亿欧元，前值为顺差42亿欧元。",
            "date_modified": "2022-09-20T08:01:20.000Z"
        },
        {
            "id": 2807015,
            "content_html": "",
            "title": "【英国明年将为乌克兰提供至少26.3亿美元的军事援助】据路透社报道，英国首相办公室当地时间9月20日表示，英国2023年对乌克兰的军事援助将达到或超过2022年的23亿英镑（约合26.3亿美元）。英国首相特拉斯办公室在一份声明中说，英国对乌克兰的军事支持可能包括多管火箭发射系统等军事装备。（央视新闻）",
            "date_modified": "2022-09-20T07:59:11.000Z"
        },
        {
            "id": 2807014,
            "content_html": "",
            "title": "【外交部：中国是推动世界经济增长的稳定器和动力源】9月20日，外交部发言人汪文斌主持例行记者会。有记者就日前国家统计局发布党的十八大以来中国经济社会发展成就系列报告提问。发言人汪文斌表示，报告显示2021年中国经济总量占世界经济的比重达到18.5%，比2012年提高了7.2个百分点。近10年间，中国对世界经济增长的平均贡献率超过30%，位居世界第一。这充分表明中国是推动世界经济增长的稳定器和动力源。近年来经济全球化遭遇逆流，单边主义保护主义上升，世界经济形势低迷，面对困难和挑战，中方坚信开放合作是历史大势，互利共赢是人心所向。我们坚持实施更大范围、更宽领域、更深层次对外开放，着力促进贸易和投资自由化、便利化，持续打造市场化、国际化、法治化营商环境，让中国市场成为世界的市场、共享的市场、大家的市场，为世界经济复苏注入更多动力和稳定性。未来，中国开放的大门不仅不会关闭，而且会越开越大。中方愿同世界各国一道，秉持开放包容、互利共赢的精神，拓展各领域务实合作，让世界各国更好分享中国发展的机遇。（央视新闻）",
            "date_modified": "2022-09-20T07:58:45.000Z"
        },
        {
            "id": 2807013,
            "content_html": "",
            "title": "【航天机电：意大利高级法院接受GSE上诉申请 确认关于削减MILIS公司电站补贴决定】航天机电公告，公司收到通知，意大利行政高级法院（简称CdS）就公司海外电站项目公司MILIS公司与意大利政府能源服务管理部门（简称GSE）关于FIT标准诉讼发布了判决结果：意大利行政高级法院接受意大利能源服务管理部门的上诉申请，确认了意大利能源服务管理部门在2018年发布的关于削减MILIS公司电站补贴的决定，推翻了2021年11月6日拉齐奥大区行政法院（TAR）出具的判决。同日公告，公司拟启动为子公司连云港新能源引入具有资源优势的外部投资者，实现对原有老旧产线的升级改造。本次拟通过国有产权交易所引入战略合作方增资总额不低于8000万元。如出资资产包含非货币性资产，须为具备生产182/210大尺寸的光伏组件产线。",
            "date_modified": "2022-09-20T07:57:55.000Z"
        },
        {
            "id": 2807012,
            "content_html": "",
            "url": "https://finance.sina.cn/7x24/2022-09-20/detail-imqqsmrn9804816.d.html",
            "title": "【世界黄金协会：预计黄金交易量和消费需求9月将回升】世界黄金协会今日发布的报告显示，若各国央行继续大力加息，黄金则可能持续承压，但经济滞胀甚至全面衰退的风险或许会抵消这一压力，因为黄金在该环境下的表现历来出色。短期来看，预计黄金交易量和消费需求9月将回升。",
            "date_modified": "2022-09-20T07:56:03.000Z"
        }
    ]
}